oxmpl_py-0.6.0.dist-info/METADATA
oxmpl_py-0.6.0.dist-info/WHEEL
oxmpl_py.libs/libgcc_s-262c4f60.so.1
oxmpl_py/__init__.py
oxmpl_py/oxmpl_py.cpython-39-arm-linux-gnueabihf.so
oxmpl_py-0.6.0.dist-info/RECORD
